asyncvarlink/__init__.py
asyncvarlink/clientprotocol.py
asyncvarlink/conversion.py
asyncvarlink/error.py
asyncvarlink/interface.py
asyncvarlink/message.py
asyncvarlink/protocol.py
asyncvarlink/py.typed
asyncvarlink/serverprotocol.py
asyncvarlink/serviceerrors.py
asyncvarlink/serviceinterface.py
asyncvarlink/types.py
asyncvarlink/util.py
asyncvarlink-0.2.1.dist-info/WHEEL
asyncvarlink-0.2.1.dist-info/METADATA
asyncvarlink-0.2.1.dist-info/RECORD
